joyrl/__init__.py
joyrl/run.py
joyrl/algos/__init__.py
joyrl/algos/A3C/__init__.py
joyrl/algos/A3C/config.py
joyrl/algos/A3C/data_handler.py
joyrl/algos/A3C/policy.py
joyrl/algos/CategoricalDQN/__init__.py
joyrl/algos/CategoricalDQN/config.py
joyrl/algos/CategoricalDQN/data_handler.py
joyrl/algos/CategoricalDQN/policy.py
joyrl/algos/DDPG/__init__.py
joyrl/algos/DDPG/config.py
joyrl/algos/DDPG/data_handler.py
joyrl/algos/DDPG/model.py
joyrl/algos/DDPG/policy.py
joyrl/algos/DQN/__init__.py
joyrl/algos/DQN/config.py
joyrl/algos/DQN/data_handler.py
joyrl/algos/DQN/policy.py
joyrl/algos/DoubleDQN/__init__.py
joyrl/algos/DoubleDQN/config.py
joyrl/algos/DoubleDQN/data_handler.py
joyrl/algos/DoubleDQN/policy.py
joyrl/algos/DuelingDQN/__init__.py
joyrl/algos/DuelingDQN/config.py
joyrl/algos/DuelingDQN/data_handler.py
joyrl/algos/DuelingDQN/policy.py
joyrl/algos/NoisyDQN/__init__.py
joyrl/algos/NoisyDQN/config.py
joyrl/algos/NoisyDQN/data_handler.py
joyrl/algos/NoisyDQN/policy.py
joyrl/algos/PPO/__init__.py
joyrl/algos/PPO/config.py
joyrl/algos/PPO/data_handler.py
joyrl/algos/PPO/policy.py
joyrl/algos/QLearning/__init__.py
joyrl/algos/QLearning/config.py
joyrl/algos/QLearning/data_handler.py
joyrl/algos/QLearning/policy.py
joyrl/algos/Sarsa/__init__.py
joyrl/algos/Sarsa/config.py
joyrl/algos/Sarsa/data_handler.py
joyrl/algos/Sarsa/policy.py
joyrl/algos/SoftQ/__init__.py
joyrl/algos/SoftQ/config.py
joyrl/algos/SoftQ/data_handler.py
joyrl/algos/SoftQ/policy.py
joyrl/algos/TD3/__init__.py
joyrl/algos/TD3/config.py
joyrl/algos/TD3/data_handler.py
joyrl/algos/TD3/model.py
joyrl/algos/TD3/policy.py
joyrl/algos/base/__init__.py
joyrl/algos/base/action_layer.py
joyrl/algos/base/base_layer.py
joyrl/algos/base/buffer.py
joyrl/algos/base/data_handler.py
joyrl/algos/base/experience.py
joyrl/algos/base/network.py
joyrl/algos/base/noise.py
joyrl/algos/base/optm.py
joyrl/algos/base/policy.py
joyrl/envs/__init__.py
joyrl/envs/blackjack.py
joyrl/envs/cliff_walking.py
joyrl/envs/gridworld.py
joyrl-0.6.8.dist-info/LICENSE
joyrl-0.6.8.dist-info/METADATA
joyrl-0.6.8.dist-info/WHEEL
joyrl-0.6.8.dist-info/entry_points.txt
joyrl-0.6.8.dist-info/top_level.txt
joyrl-0.6.8.dist-info/RECORD
