Metadata-Version: 2.1
Name: joyrl
Version: 0.6.8
Summary: A Library for Deep Reinforcement Learning
Home-page: https://github.com/datawhalechina/joyrl
Author: johnjim0816
Author-email: johnjim0816@gmail.com
License: MIT
Keywords: reinforcement learning platform pytorch
Platform: any
Requires-Python: >=3.7
License-File: LICENSE
Requires-Dist: ray[default] ==2.6.3
Requires-Dist: gymnasium ==0.29.1
Requires-Dist: gymnasium[box2d] ==0.29.1
Requires-Dist: tensorboard ==2.16.2
Requires-Dist: matplotlib ==3.8.4
Requires-Dist: seaborn ==0.13.2
Requires-Dist: dill ==0.3.8
Requires-Dist: scipy ==1.13.0
Requires-Dist: pygame ==2.5.2
Requires-Dist: swig ==4.2.1
Requires-Dist: numpy ==1.26.4
Requires-Dist: pandas ==2.2.2
Requires-Dist: six ==1.16.0
Requires-Dist: setuptools ==69.5.1
Requires-Dist: PyYAML ==6.0.1
Requires-Dist: pydantic ==1.10.15
Requires-Dist: psutil ==0.3.14
Provides-Extra: atari
Requires-Dist: atari-py ; extra == 'atari'
Requires-Dist: opencv-python ; extra == 'atari'
Provides-Extra: mujoco
Requires-Dist: mujoco-py ; extra == 'mujoco'
Provides-Extra: pybullet
Requires-Dist: pybullet ; extra == 'pybullet'
